CFBScrapy/__init__.py
CFBScrapy/cfbtools.py
CFBScrapy-0.2.0.dist-info/METADATA
CFBScrapy-0.2.0.dist-info/WHEEL
CFBScrapy-0.2.0.dist-info/top_level.txt
CFBScrapy-0.2.0.dist-info/RECORD
