Metadata-Version: 2.1
Name: CFBScrapy
Version: 0.2.0
Summary: Python wrapper for the collegefootballapi located here: https://api.collegefootballdata.com/api/docs/?url=/api-docs.json#/
Home-page: https://github.com/rlindholm/CFBScrapy
Author: Ryan Lindholm
Author-email: ryan.lindholm@outlook.com
License: UNKNOWN
Platform: UNKNOWN
Classifier: Programming Language :: Python :: 3.6
Classifier: Operating System :: OS Independent
Requires-Dist: pandas (==0.23.4)
Requires-Dist: requests (==2.21.0)
